{"ip": {"in": {"id": [13063, 13213, 13222, 13251, 14108, 14396, 14553, 14602, 15647, 15669, 15713, 16155, 16322, 16991, 17025, 18676, 18687, 18721, 20294, 20513, 20817, 20854], "ttl": 108}, "out": {"id": [33729, 33730, 33731, 33732, 33733, 33734, 33735, 33736, 33737, 33738, 33739, 33740, 33741, 33742, 33743, 33744, 33745, 33746, 33747, 33748, 33749, 33750, 33751], "ttl": 64}}, "idp_in": "450000f9339d40006c060221b2ed12ca", "time_end": 1433358092.349267, "expire_type": "a", "entropy": 1.477903, "num_pkts_out": 23, "pr": 6, "time_start": 1433358054.865487, "bytes_in": 1910, "num_pkts_in": 22, "bytes_out": 654, "byte_dist_std": 41.493359, "da": "178.237.18.202", "byte_dist_mean": 37.301872, "idp_len_out": 16, "total_entropy": 3789.342397, "byte_dist": [244, 19, 15, 5, 13, 6, 2, 3, 0, 8, 3, 3, 2, 1, 1, 0, 2, 1, 0, 0, 8, 2, 0, 3, 1, 0, 0, 0, 4, 1, 0, 3, 8, 0, 0, 0, 2, 1, 0, 0, 0, 0, 6, 0, 0, 6, 0, 3, 20, 6, 14, 1, 15, 11, 15, 6, 9, 5, 0, 0, 7, 0, 7, 0, 3, 0, 4, 0, 4, 0, 0, 0, 4, 0, 0, 0, 4, 3, 1, 4, 2, 0, 0, 0, 4, 1, 0, 0, 0, 3, 0, 0, 0, 0, 0, 0, 0, 5, 1, 4, 4, 7, 1, 0, 3, 0, 0, 0, 0, 0, 1, 6, 2, 0, 0, 0, 2, 1, 0, 0, 0, 1, 0, 0, 1, 0, 0, 0, 0, 0, 0, 0, 0, 3, 1, 0, 0, 0, 0, 0, 0, 0, 0, 0, 0, 0, 0, 0, 1, 0, 0, 0, 0, 0, 0, 0, 0, 0, 0, 0, 0, 0, 0, 0, 0, 0, 0, 0, 0, 0, 0, 0, 1, 0, 0, 0, 0, 0, 0, 0, 2, 0, 0, 0, 2, 0, 0, 0, 0, 0, 0, 0, 0, 0, 0, 0, 1, 0, 0, 0, 0, 0, 0, 0, 1, 0, 0, 0, 2, 0, 0, 0, 0, 0, 0, 0, 0, 0, 0, 0, 2, 0, 0, 0, 0, 0, 0, 0, 0, 0, 0, 0, 0, 0, 0, 0, 0, 0, 0, 0, 0, 0, 0, 0, 0, 0, 0, 0, 0, 0, 0, 0, 0, 0, 0, 3], "dp": 443, "idp_len_in": 16, "sp": 34342, "packets": [{"b": 38, "ipt": 0, "dir": ">"}, {"b": 85, "ipt": 691, "dir": ">"}, {"b": 209, "ipt": 175, "dir": "<"}, {"b": 38, "ipt": 0, "dir": ">"}, {"b": 82, "ipt": 33, "dir": "<"}, {"b": 38, "ipt": 3113, "dir": ">"}, {"b": 38, "ipt": 1301, "dir": "<"}, {"b": 259, "ipt": 676, "dir": "<"}, {"b": 38, "ipt": 150, "dir": "<"}, {"b": 100, "ipt": 4445, "dir": ">"}, {"b": 209, "ipt": 173, "dir": "<"}, {"b": 38, "ipt": 0, "dir": ">"}, {"b": 82, "ipt": 29, "dir": "<"}, {"b": 38, "ipt": 1926, "dir": ">"}, {"b": 38, "ipt": 876, "dir": "<"}, {"b": 283, "ipt": 2684, "dir": "<"}, {"b": 38, "ipt": 152, "dir": "<"}, {"b": 94, "ipt": 5919, "dir": ">"}, {"b": 209, "ipt": 174, "dir": "<"}, {"b": 38, "ipt": 0, "dir": ">"}, {"b": 82, "ipt": 29, "dir": "<"}, {"b": 38, "ipt": 5847, "dir": "<"}, {"b": 38, "ipt": 757, "dir": ">"}, {"b": 267, "ipt": 1107, "dir": "<"}, {"b": 38, "ipt": 147, "dir": "<"}, {"b": 109, "ipt": 7069, "dir": ">"}], "idp_out": "4500004e83c140004006dea70a080882", "sa": "10.8.8.130"}
{"pr": 6, "time_start": 1433358301.708274, "bytes_out": 0, "sp": 443, "packets": [], "time_end": 1433358301.708302, "da": "10.8.8.130", "ip": {"in": {"id": [1725], "ttl": 64}, "out": {"id": [15393], "ttl": 108}}, "expire_type": "i", "num_pkts_in": 1, "num_pkts_out": 1, "bytes_in": 0, "sa": "178.237.19.227", "byte_dist": [0, 0, 0, 0, 0, 0, 0, 0, 0, 0, 0, 0, 0, 0, 0, 0, 0, 0, 0, 0, 0, 0, 0, 0, 0, 0, 0, 0, 0, 0, 0, 0, 0, 0, 0, 0, 0, 0, 0, 0, 0, 0, 0, 0, 0, 0, 0, 0, 0, 0, 0, 0, 0, 0, 0, 0, 0, 0, 0, 0, 0, 0, 0, 0, 0, 0, 0, 0, 0, 0, 0, 0, 0, 0, 0, 0, 0, 0, 0, 0, 0, 0, 0, 0, 0, 0, 0, 0, 0, 0, 0, 0, 0, 0, 0, 0, 0, 0, 0, 0, 0, 0, 0, 0, 0, 0, 0, 0, 0, 0, 0, 0, 0, 0, 0, 0, 0, 0, 0, 0, 0, 0, 0, 0, 0, 0, 0, 0, 0, 0, 0, 0, 0, 0, 0, 0, 0, 0, 0, 0, 0, 0, 0, 0, 0, 0, 0, 0, 0, 0, 0, 0, 0, 0, 0, 0, 0, 0, 0, 0, 0, 0, 0, 0, 0, 0, 0, 0, 0, 0, 0, 0, 0, 0, 0, 0, 0, 0, 0, 0, 0, 0, 0, 0, 0, 0, 0, 0, 0, 0, 0, 0, 0, 0, 0, 0, 0, 0, 0, 0, 0, 0, 0, 0, 0, 0, 0, 0, 0, 0, 0, 0, 0, 0, 0, 0, 0, 0, 0, 0, 0, 0, 0, 0, 0, 0, 0, 0, 0, 0, 0, 0, 0, 0, 0, 0, 0, 0, 0, 0, 0, 0, 0, 0, 0, 0, 0, 0, 0, 0, 0, 0, 0, 0, 0, 0], "dp": 48410}
